{
    "ingresados": {
        "123": {
            "nombres": "Hola",
            "apellidos": "Perez",
            "direccion": "calle 12",
            "num_tel": 102457,
            "estados": "en proceso de inscripcion"
        },
        "7854": {
            "nombres": "Sjfa",
            "apellidos": "Dsfaj",
            "direccion": "sdfa",
            "num_tel": 74155,
            "acudiente_nombre": "Madre",
            "acudiente documento": 7415,
            "parentesco acudiente": "madre",
            "num_tel acudiente": 74555,
            "estados": "en proceso de inscripcion"
        },
        "789": {
            "nombres": "Mariana",
            "apellidos": "Pere",
            "direccion": "afasdf",
            "num_tel": 741,
            "acudiente_nombre": "Madre",
            "acudiente documento": 745,
            "parentesco acudiente": "sdff",
            "num_tel acudiente": 789,
            "estados": "en proceso de inscripcion"
        },
        "4": {
            "nombres": "E",
            "apellidos": "H",
            "direccion": "calle 13",
            "num_tel": 74,
            "acudiente_nombre": "M",
            "acudiente documento": 7,
            "parentesco acudiente": "madre",
            "num_tel acudiente": 8,
            "estados": "en proceso de inscripcion"
        },
        "7": {
            "nombres": "F",
            "apellidos": "D",
            "direccion": "12",
            "num_tel": 78,
            "acudiente_nombre": "M",
            "acudiente documento": 5,
            "parentesco acudiente": "madre",
            "num_tel acudiente": 9,
            "estados": "en proceso de inscripcion"
        },
        "9": {
            "nombres": "F",
            "apellidos": "D",
            "direccion": "f",
            "num_tel": 4,
            "estados": "en proceso de inscripcion"
        },
        "9": {
            "nombres": "D",
            "apellidos": "S",
            "direccion": "f",
            "num_tel": 7,
            "estados": "en proceso de inscripcion"
        }
    }
}